bin/__init__.py
topogram_api_client-1.0.1.dist-info/DESCRIPTION.rst
topogram_api_client-1.0.1.dist-info/METADATA
topogram_api_client-1.0.1.dist-info/RECORD
topogram_api_client-1.0.1.dist-info/WHEEL
topogram_api_client-1.0.1.dist-info/entry_points.txt
topogram_api_client-1.0.1.dist-info/metadata.json
topogram_api_client-1.0.1.dist-info/top_level.txt
topogram_client/__init__.oldies.py
topogram_client/__init__.py
