Metadata-Version: 2.0
Name: topogram-api-client
Version: 1.0.1
Summary: API Client for Topogram - Geo-network mapping.
Home-page: http://topogram.io
Author: Clement Renaud
Author-email: clement.renaud@gmail.com
License: BSD
Download-URL: https://github.com/topogram/topogram-python-client
Keywords: network,edition,api client,visualization,topogram
Platform: UNKNOWN
Classifier: Development Status :: 4 - Beta
Classifier: Environment :: Console
Classifier: Intended Audience :: Developers
Classifier: Natural Language :: English
Classifier: License :: OSI Approved :: GNU Library or Lesser General Public License (LGPL)
Classifier: Programming Language :: Python
Classifier: Programming Language :: Python :: 2.7
Classifier: Programming Language :: Python :: 3
Classifier: Topic :: Software Development
Requires-Dist: requests
